ranky.py
rank_histogram-0.2.dist-info/DESCRIPTION.rst
rank_histogram-0.2.dist-info/METADATA
rank_histogram-0.2.dist-info/RECORD
rank_histogram-0.2.dist-info/WHEEL
rank_histogram-0.2.dist-info/metadata.json
rank_histogram-0.2.dist-info/top_level.txt
